{
  "strings": {
    "sasPrivacyText": "Privacy Statement",
    "sasSurveyHeader": "Feedback",
    "sasBadLoad": "It might be that your PC isn't connected to the Internet or that our servers are down. Wait a bit, and then try again.",
    "sasBadLoadHeader": "We can't get the feedback form right now",
    "sasLoadingHeader": "Getting the feedback form"
  },
  "resources": {
    "resid-oneup-errorNoInternet": "Yanzu ba a kan layin intanet ka ke ba. Duba hanyar sadarwarka sannan ka sake gwadawa.",
    "resid-oneup-errorMediaErrSrcNotSupported": "Hotuna ba za su iya bude irin wannan fayil ba.",
    "resid-oneup-errorMediaErrNetwork": "Ba za a iya kunna bidiyon ba. Duba hanyar sadarwarka ka sake gwadawa.",
    "resid-oneup-errorMediaErrDecode": "Hotuna ba za su iya kunna wannan bidiyo ba. Watakila ta gurbace, ko kuma shirin ba zai iya bude irin wannan fayil ba.",
    "resid-oneup-errorDeviceOffline": "Yi hakuri, ba za mu iya jonawa da {{%1}} yanzu ba.",
    "resid-SetAs-Error-Unsupported": "Ba a goyon bayan wannan nauín fayil. Ɗauki wani hoto daban a kuma sake gwadawa.",
    "resid-SetAs-Error-Generic": "Ka tabbata fayilin bai ɓaci ba, a kuma sake gwadawa.",
    "resid-SetAs-Error-NoPixels": "Har yanzu ana kan loda wannan hoto. A yayin da aka gama, sake gwadawa.",
    "resid-SetAs-Error-OutOfMemory": "Ƙila ƙwaƙwalwar ajiyar wannan kwamfuta ta cika.",
    "resid-SetAs-Error-FileDoesntExist": "Ba za a sami wannan fayil ba.",
    "resid-SetAs-Error-UnauthorizedCopyOfWindows": "Kana buƙatar kunna Windows kafin ka saita kulle allon.",
    "resid-SetAs-Error-BackgroundTitle": "Ba za a iya saita wannan hoto a saman aikace-aikacen shimfiɗa ba ",
    "resid-SetAs-Error-TileTitle": "Ba za a iya saita wannan hoto a zaman tayil na aikace-aikace ba",
    "resid-SetAs-Error-LockScreenTitle": "Ba za a iya saita wannan hoto a zaman kulle allo ba",
    "resid-SetAs-BackgroundProgress": "Ana saita aikace-aikacen shimfiɗa...",
    "resid-SetAs-TileProgress": "Ana saita tayil na aikace-aikace...",
    "resid-SetAs-LockScreenProgress": "Ana saita kulle allo...",
    "resid-SharePropertyTitleVideoOnlyPlural": "Bidiyo %u",
    "resid-SharePropertyTitleVideoOnlySingular": "Bidiyo 1",
    "resid-SharePropertyTitlePhotosOnlyPlural": "Hotuna %u",
    "resid-SharePropertyTitlePhotoOnlySingular": "Hoto 1",
    "resid-SharePropertyTitlePlural": "Fayiloli %u",
    "resid-SharePropertyTitleSingular": "Fayil 1",
    "resid-SharePropertyDescriptionPlural": "Fayiloli daga aikace-aikacen Hotuna",
    "resid-SharePropertyDescriptionSingular": "Fayil daga aikace-aikacen Hotuna",
    "resid-SharePropertyTitle": "A yanzu ana kunna hotuna ko bidiyo a kan %s. Ɗan tsayar da nunin faifan a kuma sake gwadawa.",
    "resid-SharingUnderPlayToError": "Wancan aiki ba zai yiwu a halin yanzu ba saboda kana kunnawa a wata naúra. Taɓa kibiyar Baya ko a cire haɗi daga naúrar, a kuma sake gwadawa.",
    "resid-SharingDeviceOfflineError": "Ba za mu iya shiga wannan kwamfuta ba yanzu. Ka tabbata a kunne ta ke kuma a hade da layin intanet.",
    "resid-SharingDeviceVideoError": "Ba ka da halin raba bidiyon da aka adana su a wata na'urar. Dauki wani abu daban ka raba sannan ka sake gwadawa.",
    "resid-OverSharingLimitError": "Akwai fayiloli masu yawa da aka zaɓa. Zaɓi har zuwa fayiloli %u a kuma sake gwadawa.",
    "resid-NoSelectionError": "Ba abin da aka zaɓa a halin yanzu. Zaɓi wasu hotuna ko bidiyoyi a kuma sake gwadawa.",
    "resid-share-DeletingError": "Akwai buƙatar ka gama sharewa kafin ka raba fayiloli.",
    "resid-delete-SuspendedBody": "An rufe wannan aikace-aikace kafin a share duk fayiloli.",
    "resid-delete-SuspendedTitle": "Ba a iya gama share wasu fayiloli ba",
    "resid-delete-DeleteCancelButton": "Soke",
    "resid-delete-DeleteProgressString": "Ana sharewa...",
    "resid-delete-DeleteMultiFailureMessage": "A tabbata wani aikace-aikace ba ya aiki da waɗannan fayiloli, kuma kana da izini na share su.",
    "resid-delete-DeleteSingleFailureMessage": "A tabbata wani aikace-aikace ba ya aiki da wannan fayil, kuma kana da izini na share shi.",
    "resid-delete-DeleteMultiItemFailureTitleFmt": "Ba za a iya share fayiloli {{%1}} ba",
    "resid-delete-DeleteSingleItemFailureTitle": "Ba za a iya share wannan fayil ba",
    "resid-ab-SetAsBackgroundMenuTooltip": "Saita a zaman shimfiɗar aikace-aikace",
    "resid-ab-SetAsBackgroundMenuButton": "Shimfiɗar aikace-aikace",
    "resid-ab-SetAsLockScreenMenuTooltip": "Saita a zaman rufe allo",
    "resid-ab-SetAsLockScreenMenuButton": "Kulle allo",
    "resid-ab-SetAsTileMenuTooltip": "Saita a zaman tayil na aikace-aikace",
    "resid-ab-SetAsTileMenuButton": "Tayil na aikace-aikace",
    "resid-ab-SetAsTooltip": "Saita a zaman",
    "resid-ab-SetAsButton": "Saita a zaman",
    "resid-ab-ImportButton": "Shigo da",
    "resid-ab-DeleteFlyoutButton": "Share",
    "resid-ab-DeleteFlyoutMultiItemFmt": "Kana dab da share fayiloli {{%1}}.",
    "resid-ab-DeleteFlyoutSingleItem": "Kana dab da share fayil 1.",
    "resid-ab-ByAlbumTooltip": "Bincika ta kundi",
    "resid-ab-ByAlbumLabel": "Bincika ta aljihun folda",
    "resid-ab-ByDateTooltip": "Bincika ta kwanan wata",
    "resid-ab-ByDateLabel": "Bincika ta kwanan wata",
    "resid-ab-PauseVideoTooltip": "Ɗan tsaya",
    "resid-ab-PauseVideoLabel": "Ɗan tsaya",
    "resid-ab-PlayVideoTooltip": "Kunna",
    "resid-ab-PlayVideoLabel": "Kunna",
    "resid-ab-StopAutoAdvanceTooltip": "Dakatar da nunin faifai",
    "resid-ab-StopAutoAdvanceLabel": "Dakatar da nunin faifai",
    "resid-ab-DeleteTooltip": "Share",
    "resid-ab-DeleteLabel": "Share",
    "resid-ab-ViewOnlineTooltip": "Duba a kan {{%1}}",
    "resid-ab-ViewOnlineLabel": "Duba a kan {{%1}}",
    "resid-ab-BasketTooltip": "Zaɓi",
    "resid-ab-ClearTooltip": "Share zaɓi",
    "resid-ab-ClearLabel": "Share zaɓi",
    "resid-ab-SelectAllTooltip": "Zaɓi duk",
    "resid-ab-SelectAllLabel": "Zaɓi duk",
    "resid-ab-AutoAdvanceTooltip": "Nuna silaid",
    "resid-ab-AutoAdvanceLabel": "Nuna silaid",
    "resid-import-errorDiskSpace": "Ba isasshen sarari ga duk waɗannan fayiloli. Samar da wani sarari a cikin rumbu a kuma sake gwadawa.",
    "resid-import-fatalHeader": "Ba a iya ɗebowa",
    "resid-import-errorLabel": "Ba a iya shigo da fayiloli {{%1}} ba",
    "resid-import-errorHeader": "An gama ɗebowa, amma akwai wata matsala",
    "resid-import-stoppedLabel": "An shigo da fayiloli {{%1}} cikin {{%2}} zuwa Laburarin Hotuna\\{{%3}}",
    "resid-import-stoppedHeader": "An dakatar da shigarwa",
    "resid-import-gotoFolderButton": "Buɗe kundi",
    "resid-import-completeLabel": "An shigo da fayiloli {{%1}} zuwa Laburaren Hotuna\\{{%2}}",
    "resid-import-completeHeader": "An gama!",
    "resid-import-stopButton": "Dakata",
    "resid-import-closeButton": "Rufe",
    "resid-import-moreDetailButton": "Ƙarin bayanai",
    "resid-import-statusLabel": "{{%1}} cikin {{%2}}",
    "resid-import-statusHeader": "Shigowa",
    "resid-import-deviceInUseError": "Wani aikace-aikace yana amfani da wannan naúra a halin yanzu. Sake gwadawa daga baya.",
    "resid-import-deviceNotPresentError": "Ba za mu iya neman wannan naúra ba. Ka tabbata cewa an kunna ta kuma na haɗa ta da kwamfutarka.",
    "resid-import-deviceEmptyError": "Ba a iya neman wasu hotuna ko bidiyoyi a kan wannan naúra ba.",
    "resid-import-shareError": "Akwai buƙatar ka gama shigarwa kafin ka raba waɗannan fayiloli.",
    "resid-import-folderLabelSingle": "Za a shigo da fayil 1 zuwa wannan aljihun folda",
    "resid-import-folderLabelMultiple": "Za a shigo da fayiloli {{%1}} zuwa wannan aljihun folda",
    "resid-import-genericAlbumCreationError": "Wata matsala ta faru, don haka ba za a iya kirkirar makunshi ba. Sake gwadawa.",
    "resid-import-albumNameTooLongError": "Sunan makunshin ya yi tsawo da yawa. Gajarce shi sannan ka sake gwadawa.",
    "resid-import-folderInputError": "Ka tabbata cewa sunan aljihun foldarka bai ƙunshi waɗannan haruffa ba:\\ / : * ? \" < > |",
    "resid-import-ClearSelection": "Share zaɓi",
    "resid-import-SelectAll": "Zaɓi duk",
    "resid-import-folderInputLabel": "Shigo da wannan aljihun folda:",
    "resid-import-cancel": "Soke",
    "resid-import-importCommand": "Shigo da",
    "resid-import-deviceFlyoutDescriptionNoDevices": "Ka tabbata naúrarka tana kunne kuma an haɗa ta da kwamfutarka.",
    "resid-import-deviceFlyoutTitleNoDevices": "Ba a sami naúrori ba",
    "resid-import-deviceFlyoutDescription": "Idan ba ka ga an jera naúrarka ba, ka tabbata naúrarka tana kunne kuma an haɗa ta da kwamfutarka.",
    "resid-import-deviceFlyoutTitle": "Zaɓi wata naúra don ɗebowa daga gare ta",
    "resid-settings-helpNoInternetHelpLink": "Shafin Taimako",
    "resid-settings-helpNoInternetMessage": "Don samun taimako ga wannan samfuri, dole ne ka yi haɗi zuwa Intanet. Idan kana haɗe da Intanet kuma kana ganin wannan saƙo a cikin kuskure, ƙila ka ziyarci shafin taimako kai tsaye ta danna hanyar da take tafe:",
    "resid-settings-helpNoInternetTitle": "Ana Buƙatar Intanet",
    "resid-settings-defaultPhotoText": "Hoton Asali daga {{%1}}.",
    "resid-settings-copyrightStatement": "Haƙƙin Mallaka {{%1}}{{%2}}. An kare duk haƙƙoƙi.",
    "resid-settings-privacyAgreementLink": "Dokar Tsare Sirri",
    "resid-settings-endUserAgreementLink": "Yarjeniyar lasisin izinin mai amfani na Windows 8 ko Windows RT",
    "resid-settings-endUserAgreement": "{{%1}}ke gudanar da amfanin da ka ke yi da wannan manhaja.",
    "resid-settings-serviceAgreementLink": "Yarjejeniyar Ayyuka na Microsoft",
    "resid-settings-serviceAgreement": "{{%1}} ke gudanar da amfanin da ka ke yi da wannan sabis.",
    "resid-settings-publisher": "Ta {{%1}}",
    "resid-settings-aboutVersion": "Siga {{%1}}",
    "resid-settings-connectedAccountTitle": "Asusunka",
    "resid-settings-generateMoGoTiles": "Lale hotuna a kan tayil na aikace-aikace",
    "resid-settings-manageOnlineLinkNarratorText": "Zaɓuɓɓuka na {{%1}}",
    "resid-settings-manageOnlineLinkTooltipText": "Gudanar da yadda za a haɗa {{%1}} zuwa asusun Microsoft",
    "resid-settings-manageOnlineLinkText": "Zaɓuɓɓuka",
    "resid-settings-toggleOff": "A kashe",
    "resid-settings-toggleOn": "A kunne",
    "resid-settings-accountsTitle": "Nuna hotuna da bidiyo daga",
    "resid-settings-signOutConfirmationText": "Ka tabbata kana son cire akwatin adireshinka na Microsoft, da dukkan bayanansa, daga cikin wannan shiri?\n   <br><br>\n   Ba za a share ko daya daga cikin hotuna ko bidiyonka ba, amma kuma ba za a sake ganinsu a cikin shirin ba.",
    "resid-settings-signOutConfirmationButtonText": "Cire",
    "resid-settings-signOutButtonText": "Cire asusu",
    "resid-settings-notSignedInMessage": "Ba ka shiga yanzu ba",
    "resid-settings-signOutMessage": "Idan za ka canja wannan akwatin, jeka cikin Masu-amfani a saitin kwamfuta.",
    "resid-settings-photoSettingsLabel": "Zaɓuɓɓuka",
    "resid-settings-photoSettingsTitle": "Zaɓuɓɓuka",
    "resid-settings-helpLabel": "Taimako",
    "resid-settings-helpTitle": "Taimako",
    "resid-settings-aboutLabel": "Game da",
    "resid-settings-aboutTitle": "Game da Hotuna",
    "resid-singleSourceSelectionErrorFmt": "Tuni ka zaɓi fayiloli daga {{%1}}, kuma za ka iya zaɓar fayiloli ne daga tushe ɗaya a lokaci guda. Idan kana son zaɓar wannan fayil, share zaɓinka a kuma sake gwadawa.",
    "resid-picker-deviceVideo": "Babu halin daukar bidiyon da aka adana a cikin wata na'urar.",
    "resid-picker-unsupportedType": "Wannan shiri ba zai iya bude fayil din {{%1}} ba.",
    "residZoomIn": "Ƙara girma",
    "residZoomOut": "Rage girma",
    "resid-multiUpSlideshow-FindingPhotos": "Ana duba hotuna…",
    "resid-multiUpSlideshow-NoShareAllowedError": "Ba za ka iya raba wannan cakuden hoto ba.",
    "resid-multiUpSlideshow-NoPhotoError": "Babu isassun hotuna don yin cakuden hoto. Kara wasu wasu sannan ka sake gwadawa.",
    "residPhotoMix": "Kunna cakuden hoto",
    "residBack": "Baya",
    "resid-playTo-unableToPlayError": "Ba za a iya kunna wannan fayil ba.",
    "resid-playTo-genericFileError": "Wata matsala ta auku, kuma ba za mu iya kunna wannan fayil ba.",
    "resid-playTo-fileNotAvailableError": "Ba za a iya samun dama ga wannan fayil ba.",
    "resid-playTo-StatusFlyoutButton": "Buɗe Naúra",
    "resid-playTo-statusFlyoutText": "Don dakatar da kunna nuna silaid, buɗe Naúrori a kuma cire haɗi.",
    "resid-playTo-backUpDeviceName": "Naúra",
    "resid-playTo-statusTruncatedText": "Ana kunnawa zuwa...",
    "resid-playTo-headerTitleFmt": "Ana kunnawa zuwa{{%1}}",
    "resid-search-notIndexedMessageLine2": "Ɗauki wani aljihun folda daban a kuma sake gwadawa.",
    "resid-search-notIndexedMessageLine1": "Yi haƙuri, ba za mu iya neman wannan aljihun folda ba saboda ba a yi fihirrsa ba.",
    "resid-search-placeholderTextFormat": "Nema {{%1}}",
    "resid-search-emptyRemoteSearchMessageLine1Fmt": "Ba za a iya ne,an {{%1}} ba. Gwada Laburarin gida na hotunanka.",
    "resid-search-emptyLocalSearchMessageLine2": "Gwada wani nema.",
    "resid-search-emptyLocalSearchMessageLine1": "Yi haƙuri, ba mu iya samun komai ba.",
    "resid-search-searchAll": "Nemo duk",
    "resid-search-scope_N_Fmt": "Fayiloli {{%1}}a cikin {{%2}}",
    "resid-search-scope_1_Fmt": "Fayil {{%1}} a cikin{{%2}}",
    "resid-search-titleFormat": "“{{%1}}“",
    "residHideSourcesLinkNarratorText": "Ɓoye {{%1}}",
    "residHideSourcesLinkText": "Ɓoye",
    "residSignInErrorFlyoutLinkGeneric": "Ƙarin bayani",
    "residSignInErrorFlyoutTextGenericFmt": "Wani kuskure ya auku. Sake gwadawa daga baya. {{%1}}",
    "residSignInErrorFlyoutTextNoInternet": "Ka tabbata ka sake haɗi zuwa Intanet a kuma sake shiga.",
    "residConnectUpsellFlyoutText": "Za ka iya ganin hotuna da bidiyo ta cikin na'urorinka, tashoshin aiki, da kuma dandalan sadarwar na cudanya duka a wuri daya. Kafin ka fara, tabbata kana kan layin intanet.",
    "residEmptySourceMessage_EmptySourceView": "An ɓoye tushen hotonka. Don nuna wasu, canza saitunanka.",
    "residEmptySourceMessage_GenericDevice": "Aikace-aikacen Hotuna yana nuna maka hotuna da kuma bidiyoyi daga duk naúrorinka a cikin wuri guda.\n     <br><br>\n      Don ganin ƙunshiya daga wasu naúrori tafi <a href=\"http://www.SkyDrive.com/windows\">SkyDrive.com/windows</a>don zazzagewa da kuma girka Kwafin Gwaji na Microsoft SkyDrive a kansu. Sannan kuma, shiga tare da asusunka na Microsoft ka kuma tabbata an <b>Samar da fayiloli a kan wannan kwamfuta gare ni a kan sauran naúrori</b>an zaɓi akwatin zaɓi.",
    "residEmptySourceMessage_Device": "Idan kana da wani, ka tabbata ka saka su a cikin laburarin Hotunanka {{%1}}.",
    "residEmptySourceMessage_Service": "Ƙara wasu hotuna zuwa asusunka don farawa.",
    "residEmptySourceMessage_SkyDrive": "SkyDrive yana ba ka maájiyar kan layi kyauta don hotuna, bidiyoyi da kuma daftarai saboda ka sami dama gare su daga koína.\n      <br><br>\n      Tafi zuwa <a href=\"http://www.SkyDrive.com\">SkyDrive.com</a> don farawa. Za a nuna duk wasu hotuna da bidiyoyi da ka adana a nan.",
    "residEmptySourceMessage_PicturesLibrary": "Don farawa, haɗa wata naúra (kamara , waya, USB filash diraib da sauransu), ka kuma shigo ko kwafin hotuna da da bidiyoyi a cikin maádanar Hotunanka.\n     <br><br>\n     Idan tuni ka na da hotuna ko bidiyoyi a kan wannan kwamfuta, ka tabbata suna a cikin laburarinka na Hotuna. Za ka iya gudanar da laburaren Hotunanka daga File Explorer.",
    "residEmptyContainerMessage_Remote": "Ba ka da wasu hotuna a nan.",
    "residCurrentlySyncingContent-extraInfo": "This might take some time if you have a lot of photos.",
    "residCurrentlySyncingContent": "Ana sabuntawa...",
    "residEmptyContainerMessage": "Nan na cikin kaɗaici idan ba hotuna.",
    "residInlineUpsell_GenericConnect": "Jona da layin intanet",
    "residInlineUpsell_GenericDevice": "Ƙara wata naúra don ganin hotunanka",
    "residInlineUpsell_Device": "Ka kusa kaiwa...",
    "residInlineUpsell_ServiceOrPhone": "Ga naka a nan",
    "residInlineUpsell_PicturesLibrary": "Ƙara wasu hotuna",
    "residInactiveSourceTitle_Videos": "Bidiyo {{%1}}",
    "residInactiveSourceTitle_Photos": "Hotuna {{%1}}",
    "residAlbumItemCounts_Fmt": "{{%1}}, {{%2}}",
    "residAlbumCount_1_Fmt": "Aljihun folda {{%1}}",
    "residAlbumCount_N_Fmt": "Aljiuhunan folda {{%1}}",
    "residFailedThumbnailText": "Kuskure",
    "residErrorLastSyncOverOneMonthAgo": "sama da wata ɗaya da ya wuce",
    "residErrorLastSyncNDaysAgoFmt": "Ranaku {{%1}} da suka wuce",
    "residErrorLastSyncOneDayAgo": "kusan rana ɗaya da ta wuce",
    "residErrorLastSyncNHoursAgoFmt": "Awowi {{%1}} da suka wuce",
    "residErrorLastSyncLessThanTwoHoursAgo": "kusan awa ɗaya da ya wuce",
    "residErrorLastSyncLessThanOneHourAgoFmt": "Mintoci {{%1}} da suka wuce",
    "residErrorLastSyncAboutOneMinuteAgo": "kusan minti ɗaya da ya wuce",
    "residErrorSourceUnavailableMessageFmt": "Za ka iya ci gaba da ganin wasu hotuna da kuma bidiyo, amma ƙila ba sababbi ba. Sabuntawar ƙarshe ita ce {{%1}}.",
    "residErrorSourceUnavailableHeaderFmt": "Yi haƙuri, ba za mu iya haɗi zuwa {{%1}} a halin yanzu ba",
    "residErrorRemoveButtonText": "Cire hidima",
    "residErrorConnectButtonText": "Haɗa",
    "residDeviceLimitReachedErrorLink": "Sami taimako wajen gyara wannan matsala.",
    "residDeviceLimitReachedErrorInstructionTextFmt": "Akwai naúrori masu tarin yawa da aka haɗa da asusunka, saboda haka ba za ka iya ganin wasu hotuna da kuma bidiyoyi da aka adana a cikin sauran wurare a cikin wannan aikace-aikace ba. {{%1}}",
    "residServiceUnavailableInlineText": "Babu sabis",
    "residErrorTerminatedProviderInstructionFmt": "{{%1}} ƙila ya daina samuwa.",
    "residErrorServiceRemovedInstructionFmt": "{{%1}}ya daina haɗi zuwa asusunka na Microsoft. Idan kana son ci gaba da ganin ƙunshiya daga {{%1}}, sake haɗi.",
    "residErrorUpgradeableFailureInstructionText": "Ana sake haɗi don sabunta asusunka.",
    "residErrorUpgradeableFailureInlineText": "An sauya wani abu",
    "residErrorGenericFailureInstructionText": "An sami matsala. Sake gwadawa daga baya.",
    "residErrorGenericFailureInlineText": "An sami matsala",
    "residErrorDeviceOfflineInstructionText": "Je ka ka {{%1}} da tabbata ya kunna, da nasaba da Intanet. Famfo ko mamatsa da SkyDrive icon ya kuma yana haɗe yankin (kusa da dama da taskbar), to <b>Setin</b>, ku tabbata da <b>kinka Fayilolin</b> kafa na tsina a<b>Janar</b> tabu.",
    "residErrorDeviceOfflineInlineText": "Ba zai yi haɗi ba",
    "residErrorLoginFailureInstructionText": "Yi haɗi don gyara matsalar.",
    "residErrorLoginFailureInlineText": "Ba za a iya shiga ba",
    "residErrorNoNetworkConnectionInstructionText": "Ba ka yi haɗi da Intanet a halin yanzu ba kuma ba za mu iya dawo da sabuwar ƙunshiya ba.",
    "residErrorInvalidTimestampInstructionText": "Ka tabbata cewa agogon kan kwamfutarka daidai yake kuma ka sake gwadawa daga baya.",
    "residStatusUpdatingInlineText": "Ana sabuntawa...",
    "residSeconds_N_Fmt": "Daƙiƙoƙi {{%1}}",
    "residSeconds_1_Fmt": "Daƙiƙa {{%1}}",
    "residMinutes_N_Fmt": "Mintoci {{%1}}, ",
    "residMinutes_1_Fmt": "Minti {{%1}}, ",
    "residHours_N_Fmt": "Awowi{{%1}}, ",
    "residHours_1_Fmt": "Awa {{%1}}, ",
    "residVideo": "bidiyo",
    "residItemSelected": "An zaɓi {{%1}}",
    "residSelectedItemCount_1_Fmt": "An zaɓi fayil {{%1}}",
    "residSelectedItemCount_N_Fmt": "An zaɓi fayiloli {{%1}}",
    "residItemCount_1_Fmt": "Fayil {{%1}}",
    "residItemCount_N_Fmt": "Fayiloli {{%1}}",
    "resid-app-publishDate": "2012",
    "resid-app-publisher": "Kamfanin Microsoft",
    "resid-app-name": "Hotuna",
    "resid-Flickr-Photostream-Album-Name": "Photostream",
    "resid-Facebook-Video-Album-Name": "Bidiyo",
    "resid-Flickr-Service-Name": "Flickr",
    "resid-Facebook-Service-Name": "Facebook",
    "resid-Skydrive-Service-Name": "SkyDrive"
  },
  "photo": {
    "residMultiUpAlbumNameRandom": "Zagaye",
    "residAutoplayDisplayText": "Shigo da hotuna da bidiyoyi",
    "residGenericDeviceSourceName": "Na'urori",
    "residGenericConnectSourceName": "Duba hotunanka",
    "residPicturesLibrarySourceName": "Maádanar hotuna",
    "residAppDescription": "Shirin hoto yana tara duk hotunanka da finafinan da ka hada a wuri daya.",
    "residAppName": "Hotuna"
  },
  "launch": {
    "launchMandatoryUpdateText": "Don ci gaba da amfani da wannan aikace-aikace, dole ne ka sanya sabuwar sigar daga {{%1}}nan{{%2}}.",
    "launchMandatoryUpdateTitle": "Sanya sabuwar sigar"
  },
  "keylabel": {
    "residKeyLabel_\"": "\"",
    "residKeyLabel_'": "'",
    "residKeyLabel_}": "}",
    "residKeyLabel_]": "]",
    "residKeyLabel_|": "|",
    "residKeyLabel_backslash": "\\",
    "residKeyLabel_{": "{",
    "residKeyLabel_[": "[",
    "residKeyLabel_~": "~",
    "residKeyLabel_`": "`",
    "residKeyLabel_?": "?",
    "residKeyLabel_>": ">",
    "residKeyLabel_period": ".",
    "residKeyLabel__": "_",
    "residKeyLabel_<": "<",
    "residKeyLabel_,": ",",
    "residKeyLabel_=": "=",
    "residKeyLabel_:": ":",
    "residKeyLabel_;": ";",
    "residKeyLabel_scrolllock": "Scroll Lock",
    "residKeyLabel_numlock": "Num Lock",
    "residKeyLabel_f12": "F12",
    "residKeyLabel_f11": "F11",
    "residKeyLabel_f10": "F10",
    "residKeyLabel_f9": "F9",
    "residKeyLabel_f8": "F8",
    "residKeyLabel_f7": "F7",
    "residKeyLabel_f6": "F6",
    "residKeyLabel_f5": "F5",
    "residKeyLabel_f4": "F4",
    "residKeyLabel_f3": "F3",
    "residKeyLabel_f2": "F2",
    "residKeyLabel_f1": "F1",
    "residKeyLabel_forwardslash": "/",
    "residKeyLabel_-": "-",
    "residKeyLabel_plus": "+",
    "residKeyLabel_(": "(",
    "residKeyLabel_*": "*",
    "residKeyLabel_&": "&",
    "residKeyLabel_^": "^",
    "residKeyLabel_%": "%",
    "residKeyLabel_$": "$",
    "residKeyLabel_#": "#",
    "residKeyLabel_@": "@",
    "residKeyLabel_!": "!",
    "residKeyLabel_)": ")",
    "residKeyLabel_select": "Select",
    "residKeyLabel_windows": "Maɓallin Windows",
    "residKeyLabel_z": "Z",
    "residKeyLabel_y": "Y",
    "residKeyLabel_x": "X",
    "residKeyLabel_w": "W",
    "residKeyLabel_v": "V",
    "residKeyLabel_u": "U",
    "residKeyLabel_t": "T",
    "residKeyLabel_s": "S",
    "residKeyLabel_r": "R",
    "residKeyLabel_q": "Q",
    "residKeyLabel_p": "P",
    "residKeyLabel_o": "O",
    "residKeyLabel_n": "N",
    "residKeyLabel_m": "M",
    "residKeyLabel_l": "L",
    "residKeyLabel_k": "K",
    "residKeyLabel_j": "J",
    "residKeyLabel_i": "I",
    "residKeyLabel_h": "H",
    "residKeyLabel_g": "G",
    "residKeyLabel_f": "F",
    "residKeyLabel_e": "E",
    "residKeyLabel_d": "D",
    "residKeyLabel_c": "C",
    "residKeyLabel_b": "B",
    "residKeyLabel_a": "A",
    "residKeyLabel_9": "9",
    "residKeyLabel_8": "8",
    "residKeyLabel_7": "7",
    "residKeyLabel_6": "6",
    "residKeyLabel_5": "5",
    "residKeyLabel_4": "4",
    "residKeyLabel_3": "3",
    "residKeyLabel_2": "2",
    "residKeyLabel_1": "1",
    "residKeyLabel_0": "0",
    "residKeyLabel_delete": "Delete",
    "residKeyLabel_insert": "Insert",
    "residKeyLabel_downarrow": "Kibiyar Kasa",
    "residKeyLabel_rightarrow": "Kibiyar Dama",
    "residKeyLabel_uparrow": "Kibiyar Sama",
    "residKeyLabel_leftarrow": "Kibiyar Hagu",
    "residKeyLabel_home": "Home",
    "residKeyLabel_end": "End",
    "residKeyLabel_pagedown": "Page Down",
    "residKeyLabel_pageup": "Page Up",
    "residKeyLabel_space": "Spacebar",
    "residKeyLabel_escape": "Esc",
    "residKeyLabel_capslock": "Caps Lock",
    "residKeyLabel_break": "Break",
    "residKeyLabel_pause": "Pause",
    "residKeyLabel_alt": "Alt",
    "residKeyLabel_ctrl": "Ctrl",
    "residKeyLabel_shift": "Shift",
    "residKeyLabel_enter": "Enter",
    "residKeyLabel_tab": "Tab",
    "residKeyLabel_backspace": "Backspace",
    "residShortcutLabelFormat_5": "{{%1}}+{{%2}}+{{%3}}+{{%4}}+{{%5}}",
    "residShortcutLabelFormat_4": "{{%1}}+{{%2}}+{{%3}}+{{%4}}",
    "residShortcutLabelFormat_3": "{{%1}}+{{%2}}+{{%3}}",
    "residShortcutLabelFormat_2": "{{%1}}+{{%2}}"
  },
  "jx": {
    "HelpConnectionRequired": "Ya nuna kamar ba ka yo haɗi da Intanet ba. Don samun sabon Taimako, yi haɗi ka kuma sake gwadawa.",
    "AboutCopyright": "Haƙƙin Mallaka {{%1}}{{%2}}. An kare duk haƙƙoƙi.",
    "AboutPrivacyStatement": "Dokar Tsare Sirri",
    "AboutLicenseAgreementText": "Windows 8 ko Windows RT {{%1}} yana kula da amfani da wannan manhaja da kake yi.",
    "AboutLicenseAgreement": "Yarjejniyar Mai Amfani",
    "AboutServicesAgreementText": "{{%1}} yana kula da amfani da wannan sabis da kake yi.",
    "AboutServicesAgreement": "Yarjejeniyar Ayyukan Microsoft",
    "AboutPublisher": "Ta {{%1}}",
    "AboutVersion": "Siga {{%1}}",
    "Options": "Zaɓuɓɓuka",
    "Help": "Taimako",
    "About": "Game da",
    "Back": "Baya",
    "PublishDate": "2012",
    "Publisher": "Microsoft Corporation"
  }
}